modeanalyzer/__init__.py
modeanalyzer/__main__.py
modeanalyzer/dark.mplstyle
modeanalyzer/find_peaks.py
modeanalyzer/fitplotstyle
modeanalyzer/gauss.gif
modeanalyzer/gui_mpl.py
modeanalyzer/icon.gif
modeanalyzer/icon.ico
modeanalyzer/log.svg
modeanalyzer/matplotlibrc
modeanalyzer/mmi_icon.svg
modeanalyzer/modeanalyzer.py
mode_analyzer-0.1.5.dist-info/METADATA
mode_analyzer-0.1.5.dist-info/WHEEL
mode_analyzer-0.1.5.dist-info/licenses/LICENSE
mode_analyzer-0.1.5.dist-info/RECORD
