Metadata-Version: 2.1
Name: mode-analyzer
Version: 0.1.5
Summary: A GUI tool to analyze optical mode images.
Project-URL: Homepage, https://github.com/vganjali/mode-analyzer
Project-URL: Bug Tracker, https://github.com/vganjali/mode-analyzer/issues
Author-email: Vahid Ganjalizadeh <vganjali@ucsc.edu>
License: MIT License
License-File: LICENSE
Classifier: License :: OSI Approved :: MIT License
Classifier: Operating System :: OS Independent
Classifier: Programming Language :: Python :: 3
Requires-Python: >=3.7
Requires-Dist: matplotlib>=3.3.0
Requires-Dist: numpy>=1.13.3
Requires-Dist: pillow>=5.0.0
Requires-Dist: scipy>=1.0.0
